{
  "ok": true,
  "version": 1,
  "rowId": "かいりきベア|バグ|歌枠|https://www.youtube.com/watch?v=x71xevrwtRs&t=2009s",
  "generatedAt": "2026-04-14T07:56:11.512Z",
  "total": 1,
  "lastSungAt": 20250830,
  "rows": [
    {
      "artist": "かいりきベア",
      "title": "バグ",
      "kind": "歌枠",
      "dText": "20250830 【歌枠・耐久】高評価50🌟今月デビューの新人V！初耐久！耐えられる！？花彩音_3kHz かさねさんきろへるつ 【#新人vtuber】",
      "dUrl": "https://www.youtube.com/watch?v=x71xevrwtRs&t=2009s",
      "date8": 20250830,
      "rowId": "かいりきベア|バグ|歌枠|https://www.youtube.com/watch?v=x71xevrwtRs&t=2009s"
    }
  ]
}
