{
  "ok": true,
  "version": 1,
  "rowId": "9lana|balalaika(acoustic)|ショート|https://www.youtube.com/shorts/E3_s4jj9ot4",
  "generatedAt": "2026-04-14T08:15:41.455Z",
  "total": 1,
  "lastSungAt": 20250904,
  "rows": [
    {
      "artist": "9Lana",
      "title": "BALALAIKA(Acoustic)",
      "kind": "ショート",
      "dText": "20250904 BALALAIKA(Acoustic)/9Lana #歌ってみた #acoustic #9lana #vtuber",
      "dUrl": "https://www.youtube.com/shorts/E3_s4jj9ot4",
      "date8": 20250904,
      "rowId": "9lana|balalaika(acoustic)|ショート|https://www.youtube.com/shorts/E3_s4jj9ot4"
    }
  ]
}
