{
  "ok": true,
  "version": 1,
  "rowId": "kanaria|酔いどれ知らず|歌枠|https://www.youtube.com/watch?v=mdeFS8kgFcM&t=3058s",
  "generatedAt": "2026-04-15T02:29:57.006Z",
  "total": 1,
  "lastSungAt": 20260121,
  "rows": [
    {
      "artist": "kanaria",
      "title": "酔いどれ知らず",
      "kind": "歌枠",
      "dText": "20260121 【#歌枠 昼の部】初見歓迎🌟午後からのんびり歌います⚛️🌐花彩音_3kHz かさねさんきろへるつ 【#新人vtuber】",
      "dUrl": "https://www.youtube.com/watch?v=mdeFS8kgFcM&t=3058s",
      "date8": 20260121,
      "rowId": "kanaria|酔いどれ知らず|歌枠|https://www.youtube.com/watch?v=mdeFS8kgFcM&t=3058s"
    }
  ]
}
